cinnavo/__init__.py
cinnavo/client.py
cinnavo/exceptions.py
cinnavo/utils.py
cinnavo-0.1.0.dist-info/METADATA
cinnavo-0.1.0.dist-info/WHEEL
cinnavo-0.1.0.dist-info/top_level.txt
cinnavo-0.1.0.dist-info/RECORD
