Metadata-Version: 2.1
Name: cinnavo
Version: 0.1.0
Summary: Python client for interacting with the Cinnavo API
Home-page: https://github.com/yourusername/cinnavo
Author: Nitya Singh
Author-email: nitya@cinnavo.com
Classifier: Programming Language :: Python :: 3
Classifier: License :: OSI Approved :: MIT License
Requires-Dist: requests
